mmkg_mm_entity_linking/__init__.py
mmkg_mm_entity_linking/app.py
mmkg_mm_entity_linking/bpe_simple_vocab_16e6.txt.gz
mmkg_mm_entity_linking/classes.txt
mmkg_mm_entity_linking/clip.py
mmkg_mm_entity_linking/model.py
mmkg_mm_entity_linking/models.py
mmkg_mm_entity_linking/simple_tokenizer.py
mmkg_mm_entity_linking-0.1.2.dist-info/METADATA
mmkg_mm_entity_linking-0.1.2.dist-info/WHEEL
mmkg_mm_entity_linking-0.1.2.dist-info/top_level.txt
mmkg_mm_entity_linking-0.1.2.dist-info/RECORD
