Metadata-Version: 2.1
Name: mmkg-mm-entity-linking
Version: 0.1.2
Summary: MMKG Models
Home-page: https://github.com/vivym/mmkg-mm-entity-linking
Download-URL: https://github.com/vivym/mmkg-mm-entity-linking/tags
Author: Ming Yang
Author-email: ymviv@qq.com
Requires-Python: >=3.9
Requires-Dist: pillow
Requires-Dist: aiofiles
Requires-Dist: fastapi
Requires-Dist: uvicorn[standard]
Requires-Dist: python-multipart
Requires-Dist: ftfy
Requires-Dist: regex
Requires-Dist: tqdm
